michaniskin_pypi_test/__init__.py
michaniskin_pypi_test/main.py
michaniskin_pypi_test-0.1.0.dist-info/entry_points.txt
michaniskin_pypi_test-0.1.0.dist-info/WHEEL
michaniskin_pypi_test-0.1.0.dist-info/METADATA
michaniskin_pypi_test-0.1.0.dist-info/RECORD
