Metadata-Version: 2.1
Name: michaniskin-pypi-test
Version: 0.1.0
Summary: 
Author: Micha Niskin
Author-email: micha.niskin@gmail.com
Requires-Python: >=3.9,<4.0
Classifier: Programming Language :: Python :: 3
Classifier: Programming Language :: Python :: 3.10
Classifier: Programming Language :: Python :: 3.9
Requires-Dist: typer[all] (>=0.6.1,<0.7.0)
